htb/__init__.py
htb/cli.py
htb/client.py
htb/config.py
htb/formatters.py
htb/commands/__init__.py
htb/commands/challenges.py
htb/commands/machines.py
htb/commands/season.py
htb/commands/sherlocks.py
htb/commands/vpn.py
htb_terminal-1.0.0.dist-info/METADATA
htb_terminal-1.0.0.dist-info/WHEEL
htb_terminal-1.0.0.dist-info/entry_points.txt
htb_terminal-1.0.0.dist-info/licenses/LICENSE
htb_terminal-1.0.0.dist-info/RECORD
