Metadata-Version: 2.4
Name: htb-terminal
Version: 1.0.0
Summary: Clean, modular CLI for Hack The Box Labs API
Project-URL: Homepage, https://github.com/Shadow21AR/htb-cli
Project-URL: Repository, https://github.com/Shadow21AR/htb-cli
Author: sado
License: MIT
License-File: LICENSE
Keywords: cli,ctf,hackthebox,htb,security
Classifier: Development Status :: 4 - Beta
Classifier: Environment :: Console
Classifier: Intended Audience :: Developers
Classifier: Intended Audience :: Information Technology
Classifier: License :: OSI Approved :: MIT License
Classifier: Operating System :: OS Independent
Classifier: Programming Language :: Python :: 3
Classifier: Programming Language :: Python :: 3.10
Classifier: Programming Language :: Python :: 3.11
Classifier: Programming Language :: Python :: 3.12
Classifier: Topic :: Security
Classifier: Topic :: Utilities
Requires-Python: >=3.10
Requires-Dist: httpx>=0.27.0
Requires-Dist: rich>=13.0.0
Requires-Dist: typer>=0.9.0
Provides-Extra: dev
Requires-Dist: pytest-cov>=4.0.0; extra == 'dev'
Requires-Dist: pytest>=7.0.0; extra == 'dev'
Requires-Dist: ruff>=0.1.0; extra == 'dev'
